{"name":"Allure 3 Report","stats":{"total":4200,"passed":4177,"unknown":12,"retries":66,"skipped":10,"failed":1},"status":"failed","duration":952102,"createdAt":1771407398221,"plugin":"Awesome","newTests":[{"id":"ef9c651902f389e3771d4940eec671f4","name":"should return empty array if limit is zero","status":"passed","duration":2},{"id":"34199487180b27d381a242f5911009b7","name":"should throw if limit is negative","status":"passed","duration":4},{"id":"5bdae7207fec1d6819a317f28fc40234","name":"should return empty array if file does not exist","status":"passed","duration":5},{"id":"6302f1d3e442088a3d68b8590cac5325","name":"should overwrite file with single entry if limit is one","status":"passed","duration":5},{"id":"b0cb4df96d0acbe6af195f710625bc05","name":"should make file empty if limit is zero","status":"passed","duration":4},{"id":"423e5e05887e9deb888827caf1730b3b","name":"should append entry to existing file if limit is not defined","status":"passed","duration":6},{"id":"8416790a71e6f8990b29e6051a881eb1","name":"should return empty array if file is empty","status":"passed","duration":6},{"id":"38c7328964df7d90c9dc5e786dbfa095","name":"should return all entries if limit equals 1","status":"passed","duration":3},{"id":"828430c1f9530ab541c7fd858244a2d8","name":"should return the last entry if limit is 1","status":"passed","duration":2},{"id":"2ba953a47a20d7ee40020ed3b0868295","name":"should get the last entry only if limit is 1","status":"passed","duration":6},{"id":"8a78678f5c96e42c9aec85e2e627772e","name":"should return an empty array if limit is zero","status":"passed","duration":2},{"id":"0826304b0e4be8d23eb4422182fd61c4","name":"should append the entry if limit is greater than one","status":"passed","duration":6},{"id":"690165dd3d09b239ae3feab7f5c8860e","name":"should return the second entry if limit is 1","status":"passed","duration":2},{"id":"c495d0c204a45deef953031f4a6cbe4a","name":"should rotate without decoding if limit is 2","status":"passed","duration":7},{"id":"da72d41f47b9b7ebfece5c392ada75dc","name":"should write entry to new file if limit is not defined","status":"passed","duration":7},{"id":"1f0f442a47847372cf1ef8db73290172","name":"should return all entries if no limit specified","status":"passed","duration":2},{"id":"109e9a954543581938fd5b66c4e5588d","name":"should overwrite the entry if limit is one","status":"passed","duration":5},{"id":"b02a4c50cc74f2fa55011edc70780292","name":"should append entry to existing file if limit is positive","status":"passed","duration":5},{"id":"2daf8a6420eba4406cd9a50da49962d8","name":"should return all entries if limit is greater than 1","status":"passed","duration":2},{"id":"760d09c34209ea3d41255647c6cad6d1","name":"should make file empty if limit is zero","status":"passed","duration":4},{"id":"a29fdb434cccd542e33a2f763cf3b909","name":"should not read entries that are trimmed by the limit","status":"passed","duration":2},{"id":"6b5799b876eb8d8f23181f95bcd31a3f","name":"should return the latest two entries if limit is 2","status":"passed","duration":2},{"id":"196b32e3db4f2182767a9f7c40432604","name":"should return all entries if no limit specified","status":"passed","duration":3},{"id":"c949ee302e69a224f71e78c2b773380d","name":"should create empty file if limit is zero","status":"passed","duration":7},{"id":"1efe9c632e7551ee69368849ea665e35","name":"should keep file empty if limit is zero","status":"passed","duration":4},{"id":"837b2798529eefa2c5f39e1183998095","name":"should not parse the existing content when rotating","status":"passed","duration":13},{"id":"7c21bccb33bc6e00140bbc83b0bfd528","name":"should append without decoding if limit is greater than 2","status":"passed","duration":9},{"id":"e515513cdb36047b30964848df3f984a","name":"should append the entry if limit is greater than two","status":"passed","duration":5},{"id":"8baab3b910cef2aa592642447db748a8","name":"should return all entries if no limit specified","status":"passed","duration":2},{"id":"a942ca85b5735de921806205a66bf635","name":"should write entry to new file if limit is positive","status":"passed","duration":4},{"id":"c656afbefebafe4d2f82326da11c42b1","name":"should rotate the entries if limit is two","status":"passed","duration":5},{"id":"4676d9b8b96593c664c7d6d5aedc9f57","name":"should return an empty array if limit is zero","status":"passed","duration":2},{"id":"bfd5cd8fed717b9a7031029cd1d5a2e0","name":"should not hit MAX_STRING_LENGTH","status":"passed","duration":11764},{"id":"48725902715068f39321330d9bcee5f5","name":"should overwrite the entry if limit is one","status":"passed","duration":2},{"id":"bece5ec58e00c0fb234bd48f0504937a","name":"should rotate the entries if limit is two","status":"passed","duration":3},{"id":"d28585445f826e2655a9593f37f2a3f1","name":"should not parse the existing content when rotating","status":"passed","duration":3},{"id":"1e6cec6a6b4cb634cc7aca44c219740b","name":"should not read entries that are trimmed by the limit","status":"passed","duration":2},{"id":"bd2c4f885eaac96927ba8d3dabcaa460","name":"should return all entries if limit equals 1","status":"passed","duration":2},{"id":"cc062bfeb91d6184c2392301187cf5a8","name":"should append the entry if limit is greater than two","status":"passed","duration":3},{"id":"d7e6078ba15221f5717c43e8d129ad5d","name":"should return empty array if file does not exist","status":"passed","duration":3},{"id":"b8a9bed05857b1eb4a8c1157cdb21a8a","name":"should overwrite file with single entry if limit is one","status":"passed","duration":3},{"id":"b48a475d7148731e5da20073e8067110","name":"should throw if limit is negative","status":"passed","duration":2},{"id":"0aa6d46aba480fa68295f110d99e1088","name":"should return all entries if limit is greater than 1","status":"passed","duration":2},{"id":"4f875c3c440d9579f0ceec52c4d835ea","name":"should get the last entry only if limit is 1","status":"passed","duration":6},{"id":"7ac0386be8c088fff1c3bf871b1105a0","name":"should not hit MAX_STRING_LENGTH","status":"passed","duration":9838},{"id":"ebe078ae58f589a9ae206cd69ce02ae0","name":"should keep file empty if limit is zero","status":"passed","duration":2},{"id":"4b37e7d77f97dae97202319c2413f523","name":"should write entry to new file if limit is positive","status":"passed","duration":2},{"id":"d0d18307ed905bb45c349ac9da191ae1","name":"should return empty array if limit is zero","status":"passed","duration":1},{"id":"3e6a06ef204f7430feb8ee0b9b25c659","name":"should return all entries if no limit specified","status":"passed","duration":2},{"id":"28e9c7e360e1b1cd1601305e8646c754","name":"should return the latest two entries if limit is 2","status":"passed","duration":2},{"id":"85df905d68804910ba937a874dd83d3e","name":"should return the last entry if limit is 1","status":"passed","duration":1},{"id":"82b13363650deec9d671fc295d2ec27a","name":"should return an empty array if limit is zero","status":"passed","duration":1},{"id":"ea5c224d2d3432cbb6de082221a6fbd0","name":"should return an empty array if limit is zero","status":"passed","duration":1},{"id":"22c7e775f189d16f60f14328a6b13a7c","name":"should create empty file if limit is zero","status":"passed","duration":3},{"id":"f9dba8df42d5164e7098188b31628c39","name":"should write entry to new file if limit is not defined","status":"passed","duration":4},{"id":"223ed6f1871445ea3e6b2542462f7768","name":"should return empty array if file is empty","status":"passed","duration":8},{"id":"301ec63e3ac646c6015e6b0e48f54300","name":"should rotate without decoding if limit is 2","status":"passed","duration":3},{"id":"37b5562c92845cfaa090ef12d4bae76c","name":"should make file empty if limit is zero","status":"passed","duration":2},{"id":"2dcad3cef2f3aedfc30567f6b63063d8","name":"should make file empty if limit is zero","status":"passed","duration":2},{"id":"607e2f009e9c5f1de2377044ae30c011","name":"should append entry to existing file if limit is not defined","status":"passed","duration":3},{"id":"a9be8452dc88c1219fc686d00aadb469","name":"should append entry to existing file if limit is positive","status":"passed","duration":2},{"id":"e74f3de855e1ca3ba99e5b9a55e8b562","name":"should return all entries if no limit specified","status":"passed","duration":4},{"id":"bfec5758836db7e3beeffe1d3a2b921e","name":"should append without decoding if limit is greater than 2","status":"passed","duration":2},{"id":"82d8f45c5758a209500e07f84bc397be","name":"should return the second entry if limit is 1","status":"passed","duration":2},{"id":"d5f5df85ea936508a3b3f59c7d21e798","name":"should return all entries if no limit specified","status":"passed","duration":2},{"id":"2282a3e42b74965169e0db9400c74a16","name":"should append the entry if limit is greater than one","status":"passed","duration":2}],"flakyTests":[],"retryTests":[],"meta":{"reportId":"a6ce1859-06f6-4d4d-afe0-8c59f0b2ade6","singleFile":false,"withTestResultsLinks":true},"pullRequestHref":"","jobHref":"https://github.com/allure-framework/allure3/actions/runs/22133166328","remoteHref":"https://dev-storage-service.allurereport.org/a6ce1859-06f6-4d4d-afe0-8c59f0b2ade6/awesome/"}