{"stats":{"total":5134,"passed":5107,"retries":84,"unknown":12,"skipped":15},"status":"passed","newTests":[],"flakyTests":[],"retryTests":[],"name":"My Dashboard","duration":1566152,"createdAt":1772807669331,"plugin":"Dashboard","meta":{"reportId":"a3e61ca8-541c-4a74-8a5e-98b30046c72d","singleFile":false},"pullRequestHref":"","jobHref":"https://github.com/allure-framework/allure3/actions/runs/22766788416","remoteHref":"https://dev-storage-service.allurereport.org/a3e61ca8-541c-4a74-8a5e-98b30046c72d/dashboard/"}